<?xml version="1.0" encoding="UTF-8"?>
<objects serializationModel="Studio.01.10.00">
    <object class="AudioFile" id="{e87a3370-6f49-4187-b813-96ce253e2863}">
        <property name="assetPath">
            <value>SFX/sfx_static_01.wav</value>
        </property>
        <property name="frequencyInKHz">
            <value>48</value>
        </property>
        <property name="channelCount">
            <value>1</value>
        </property>
        <property name="length">
            <value>4</value>
        </property>
        <relationship name="masterAssetFolder">
            <destination>{f95f8411-0ad7-4f7b-afa3-04f4f12f5933}</destination>
        </relationship>
    </object>
</objects>
